barrins_codex/__init__.py
barrins_codex/card_list.py
barrins_codex/config.py
barrins_codex/navigation.py
barrins_codex/static/robots.txt
barrins_codex/static/css/body.css
barrins_codex/static/css/dropdown_menu.css
barrins_codex/static/css/fonts.css
barrins_codex/static/css/footer.css
barrins_codex/static/css/header.css
barrins_codex/static/fonts/fa-brands-400.eot
barrins_codex/static/fonts/fa-brands-400.svg
barrins_codex/static/fonts/fa-brands-400.ttf
barrins_codex/static/fonts/fa-brands-400.woff
barrins_codex/static/fonts/fa-brands-400.woff2
barrins_codex/static/fonts/fa-solid-900.eot
barrins_codex/static/fonts/fa-solid-900.svg
barrins_codex/static/fonts/fa-solid-900.ttf
barrins_codex/static/fonts/fa-solid-900.woff
barrins_codex/static/fonts/fa-solid-900.woff2
barrins_codex/static/img/banner.jpg
barrins_codex/static/img/codex.jpg
barrins_codex/static/img/favicon.ico
barrins_codex/static/img/icons/codex.svg
barrins_codex/static/img/icons/discord.png
barrins_codex/static/img/icons/twitch.png
barrins_codex/static/img/icons/twitter.png
barrins_codex/static/img/matchs/1-adeliz-vs-kinnan.jpg
barrins_codex/static/img/matchs/10-kari-zev-vs-marath.jpg
barrins_codex/static/img/matchs/11-doran-vs-marchesa.jpg
barrins_codex/static/img/matchs/12-light-paws-vs-ishaitevesh.jpg
barrins_codex/static/img/matchs/13-bjornawernog-vs-grist.jpg
barrins_codex/static/img/matchs/14-minsc-vs-shorikai.jpg
barrins_codex/static/img/matchs/15-dennick-vs-hinata.jpg
barrins_codex/static/img/matchs/16-aminatou-vs-tiamat.jpg
barrins_codex/static/img/matchs/17-grist-vs-sythis.jpg
barrins_codex/static/img/matchs/18-kari-zev-vs-killian-budget.jpg
barrins_codex/static/img/matchs/19-elmarsophina-vs-shorikai.jpg
barrins_codex/static/img/matchs/2-kari-zev-vs-saskia.jpg
barrins_codex/static/img/matchs/20-juri-vs-sai.jpg
barrins_codex/static/img/matchs/21-aminatou-vs-beamtown.jpg
barrins_codex/static/img/matchs/22-raffine-vs-tivit.jpg
barrins_codex/static/img/matchs/23-karlov-vs-reality-chip.jpg
vod_barrins_codex-0.0.5.dist-info/LICENSE
vod_barrins_codex-0.0.5.dist-info/METADATA
vod_barrins_codex-0.0.5.dist-info/WHEEL
vod_barrins_codex-0.0.5.dist-info/entry_points.txt
vod_barrins_codex-0.0.5.dist-info/top_level.txt
vod_barrins_codex-0.0.5.dist-info/zip-safe
vod_barrins_codex-0.0.5.dist-info/RECORD
