Metadata-Version: 2.1
Name: vod-barrins-codex
Version: 0.0.5
Summary: "A Collection of Duel Commander commented games in French",
Home-page: https://github.com/Spigushe/barrins-codex
Author: mcuchet
Author-email: martin.cuchet@gmail.com
License: "MIT"
Keywords: mtg strategy duel-commander edh commander
Classifier: Development Status :: 4 - Beta
Classifier: Intended Audience :: Other Audience
Classifier: Natural Language :: French
Classifier: Operating System :: OS Independent
Classifier: Environment :: Console
Classifier: Programming Language :: Python :: 3
Classifier: Programming Language :: Python :: 3.8
Classifier: Topic :: Other/Nonlisted Topic
License-File: LICENSE
Requires-Dist: flask
Requires-Dist: unidecode
Requires-Dist: requests
Provides-Extra: dev
Requires-Dist: black ; extra == 'dev'
Requires-Dist: clipboard ; extra == 'dev'
Requires-Dist: flake8 ; extra == 'dev'
Requires-Dist: ipython ; extra == 'dev'
Requires-Dist: pytest ; extra == 'dev'
Requires-Dist: zest.releaser[recommended] ; extra == 'dev'
